<?xml version="1.0" encoding="utf-8" ?>
<dwsync>
<file name="aengstlichkeit.php" server="ftp.lalala.abcde.biz//ja2.cc/" local="129667684772343750" remote="129667699800000000" />
<file name="befangenheit.php" server="ftp.lalala.abcde.biz//ja2.cc/" local="129667686367500000" remote="129667699800000000" />
<file name="pessimismus.php" server="ftp.lalala.abcde.biz//ja2.cc/" local="129667685901718750" remote="129667699800000000" />
<file name="reizbarkeit.php" server="ftp.lalala.abcde.biz//ja2.cc/" local="129667685345937500" remote="129667699800000000" />
<file name="verletzlichkeit.php" server="ftp.lalala.abcde.biz//ja2.cc/" local="129667687180937500" remote="129667699800000000" />
<file name="impulsivitaet.php" server="ftp.lalala.abcde.biz//ja2.cc/" local="129667686818593750" remote="129667699800000000" />
<file name="aengstlichkeit.php" server="F:/Projekte/xampp/htdocs/PJ13/" local="129667684772343750" remote="129667684770000000" />
<file name="befangenheit.php" server="F:/Projekte/xampp/htdocs/PJ13/" local="129667686367500000" remote="129667686360000000" />
<file name="impulsivitaet.php" server="F:/Projekte/xampp/htdocs/PJ13/" local="129667686818593750" remote="129667686810000000" />
<file name="pessimismus.php" server="F:/Projekte/xampp/htdocs/PJ13/" local="129667685901718750" remote="129667685900000000" />
<file name="reizbarkeit.php" server="F:/Projekte/xampp/htdocs/PJ13/" local="129667685345937500" remote="129667685340000000" />
<file name="verletzlichkeit.php" server="F:/Projekte/xampp/htdocs/PJ13/" local="129667687180937500" remote="129667687180000000" />
</dwsync>